[
  {
    "id": "c9c9f343-b96c-11e4-a802-0aaa78deedf9",
    "type": "Motion",
    "description": "2 People Shaking Hands Part 1 -  Female",
    "category": "",
    "character_type": "human",
    "name": "Shaking Hands 1",
    "thumbnail": "https://d99n9xvb9513w.cloudfront.net/thumbnails/motions/119070901/static.png",
    "thumbnail_animated": "https://d99n9xvb9513w.cloudfront.net/thumbnails/motions/119070901/animated.gif",
    "motion_id": "c9c9f343-b96c-11e4-a802-0aaa78deedf9",
    "motions": null,
    "source": "system"
  },
  {
    "id": "c9c9dd2f-b96c-11e4-a802-0aaa78deedf9",
    "type": "Motion",
    "description": "Diagonal Wall Run To Jumping",
    "category": "",
    "character_type": "human",
    "name": "Diagonal Wall Run",
    "thumbnail": "https://d99n9xvb9513w.cloudfront.net/thumbnails/motions/118790901/static.png",
    "thumbnail_animated": "https://d99n9xvb9513w.cloudfront.net/thumbnails/motions/118790901/animated.gif",
    "motion_id": "c9c9dd2f-b96c-11e4-a802-0aaa78deedf9",
    "motions": null,
    "source": "system"
  },
  {
    "id": "c9c9ea58-b96c-11e4-a802-0aaa78deedf9",
    "type": "Motion",
    "description": "Standing Backflip",
    "category": "",
    "character_type": "human",
    "name": "Backflip",
    "thumbnail": "https://d99n9xvb9513w.cloudfront.net/thumbnails/motions/118400901/static.png",
    "thumbnail_animated": "https://d99n9xvb9513w.cloudfront.net/thumbnails/motions/118400901/animated.gif",
    "motion_id": "c9c9ea58-b96c-11e4-a802-0aaa78deedf9",
    "motions": null,
    "source": "system"
  },
  {
    "id": "c9c8b4dd-b96c-11e4-a802-0aaa78deedf9",
    "type": "Motion",
    "description": "Climb Through Fence And Jump Down",
    "category": "",
    "character_type": "human",
    "name": "Climbing Down",
    "thumbnail": "https://d99n9xvb9513w.cloudfront.net/thumbnails/motions/135680901/static.png",
    "thumbnail_animated": "https://d99n9xvb9513w.cloudfront.net/thumbnails/motions/135680901/animated.gif",
    "motion_id": "c9c8b4dd-b96c-11e4-a802-0aaa78deedf9",
    "motions": null,
    "source": "system"
  },
  {
    "id": "c9c8236b-b96c-11e4-a802-0aaa78deedf9",
    "type": "Motion",
    "description": "Throwing Something Holding Rifle Aimed",
    "category": "",
    "character_type": "human",
    "name": "Toss Grenade",
    "thumbnail": "https://d99n9xvb9513w.cloudfront.net/thumbnails/motions/115870901/static.png",
    "thumbnail_animated": "https://d99n9xvb9513w.cloudfront.net/thumbnails/motions/115870901/animated.gif",
    "motion_id": "c9c8236b-b96c-11e4-a802-0aaa78deedf9",
    "motions": null,
    "source": "system"
  },
  {
    "id": "c9c6c6ad-b96c-11e4-a802-0aaa78deedf9",
    "type": "Motion",
    "description": "Smash With Back Of Rifle Or Staff",
    "category": "",
    "character_type": "human",
    "name": "Smash",
    "thumbnail": "https://d99n9xvb9513w.cloudfront.net/thumbnails/motions/104760901/static.png",
    "thumbnail_animated": "https://d99n9xvb9513w.cloudfront.net/thumbnails/motions/104760901/animated.gif",
    "motion_id": "c9c6c6ad-b96c-11e4-a802-0aaa78deedf9",
    "motions": null,
    "source": "system"
  },
  {
    "id": "c9c69537-b96c-11e4-a802-0aaa78deedf9",
    "type": "Motion",
    "description": "Shoulder Shrug",
    "category": "",
    "character_type": "human",
    "name": "Shrugging",
    "thumbnail": "https://d99n9xvb9513w.cloudfront.net/thumbnails/motions/102860905/static.png",
    "thumbnail_animated": "https://d99n9xvb9513w.cloudfront.net/thumbnails/motions/102860905/animated.gif",
    "motion_id": "c9c69537-b96c-11e4-a802-0aaa78deedf9",
    "motions": null,
    "source": "system"
  },
  {
    "id": "c9c5ed32-b96c-11e4-a802-0aaa78deedf9",
    "type": "Motion",
    "description": "Waving",
    "category": "",
    "character_type": "human",
    "name": "Waving",
    "thumbnail": "https://d99n9xvb9513w.cloudfront.net/thumbnails/motions/103020901/static.png",
    "thumbnail_animated": "https://d99n9xvb9513w.cloudfront.net/thumbnails/motions/103020901/animated.gif",
    "motion_id": "c9c5ed32-b96c-11e4-a802-0aaa78deedf9",
    "motions": null,
    "source": "system"
  },
  {
    "id": "80d21026-ee2c-48d4-8025-e8e51d4366df",
    "type": "Motion",
    "description": "Turning 90 Degrees Right With Torch",
    "category": "",
    "character_type": "human",
    "name": "Standing Torch Turn Right 90",
    "thumbnail": "https://d99n9xvb9513w.cloudfront.net/thumbnails/motions/128690940/static.png",
    "thumbnail_animated": "https://d99n9xvb9513w.cloudfront.net/thumbnails/motions/128690940/animated.gif",
    "motion_id": "80d21026-ee2c-48d4-8025-e8e51d4366df",
    "motions": null,
    "source": "system"
  },
  {
    "id": "fa11c97b-2179-4ed3-8cd4-df479e177f4f",
    "type": "Motion",
    "description": "Running Right With Torch",
    "category": "",
    "character_type": "human",
    "name": "Standing Torch Run Right",
    "thumbnail": "https://d99n9xvb9513w.cloudfront.net/thumbnails/motions/128690935/static.png",
    "thumbnail_animated": "https://d99n9xvb9513w.cloudfront.net/thumbnails/motions/128690935/animated.gif",
    "motion_id": "fa11c97b-2179-4ed3-8cd4-df479e177f4f",
    "motions": null,
    "source": "system"
  },
  {
    "id": "26b4d230-9615-468e-a32a-8b77084ded60",
    "type": "Motion",
    "description": "Legs Crossed, Arms Raised",
    "category": "",
    "character_type": "human",
    "name": "Female Standing Pose",
    "thumbnail": "https://d99n9xvb9513w.cloudfront.net/thumbnails/motions/140700911/static.png",
    "thumbnail_animated": "https://d99n9xvb9513w.cloudfront.net/thumbnails/motions/140700911/animated.gif",
    "motion_id": "26b4d230-9615-468e-a32a-8b77084ded60",
    "motions": null,
    "source": "system"
  },
  {
    "id": "a9ee80a2-21bf-4878-b858-55d5613c1331",
    "type": "Motion",
    "description": "Leaning Backwards, Arms Supporting",
    "category": "",
    "character_type": "human",
    "name": "Male Sitting Pose",
    "thumbnail": "https://d99n9xvb9513w.cloudfront.net/thumbnails/motions/150600905/static.png",
    "thumbnail_animated": "https://d99n9xvb9513w.cloudfront.net/thumbnails/motions/150600905/animated.gif",
    "motion_id": "a9ee80a2-21bf-4878-b858-55d5613c1331",
    "motions": null,
    "source": "system"
  },
  {
    "id": "b414a4b5-236d-46e3-a2bd-efd45612ec42",
    "type": "Motion",
    "description": "Running Forward",
    "category": "",
    "character_type": "human",
    "name": "Male Locomotion Pose",
    "thumbnail": "https://d99n9xvb9513w.cloudfront.net/thumbnails/motions/150500904/static.png",
    "thumbnail_animated": "https://d99n9xvb9513w.cloudfront.net/thumbnails/motions/150500904/animated.gif",
    "motion_id": "b414a4b5-236d-46e3-a2bd-efd45612ec42",
    "motions": null,
    "source": "system"
  },
  {
    "id": "6cfc15ef-1805-467c-8936-269289fd0c62",
    "type": "Motion",
    "description": "Turning 90 Degrees Left",
    "category": "",
    "character_type": "human",
    "name": "Crouch Torch Turn Left 90",
    "thumbnail": "https://d99n9xvb9513w.cloudfront.net/thumbnails/motions/128690904/static.png",
    "thumbnail_animated": "https://d99n9xvb9513w.cloudfront.net/thumbnails/motions/128690904/animated.gif",
    "motion_id": "6cfc15ef-1805-467c-8936-269289fd0c62",
    "motions": null,
    "source": "system"
  },
  {
    "id": "b81a8d54-0f09-4c56-8f4d-243bd3d9aa9c",
    "type": "Motion",
    "description": "Sitting Backwards On Chair, Hands Relaxed",
    "category": "",
    "character_type": "human",
    "name": "Male Sitting Pose",
    "thumbnail": "https://d99n9xvb9513w.cloudfront.net/thumbnails/motions/150600917/static.png",
    "thumbnail_animated": "https://d99n9xvb9513w.cloudfront.net/thumbnails/motions/150600917/animated.gif",
    "motion_id": "b81a8d54-0f09-4c56-8f4d-243bd3d9aa9c",
    "motions": null,
    "source": "system"
  },
  {
    "id": "31b59770-4380-4514-a47b-c702f8c9c593",
    "type": "Motion",
    "description": "Floating, Back Arched",
    "category": "",
    "character_type": "human",
    "name": "Female Dynamic Pose",
    "thumbnail": "https://d99n9xvb9513w.cloudfront.net/thumbnails/motions/140300905/static.png",
    "thumbnail_animated": "https://d99n9xvb9513w.cloudfront.net/thumbnails/motions/140300905/animated.gif",
    "motion_id": "31b59770-4380-4514-a47b-c702f8c9c593",
    "motions": null,
    "source": "system"
  },
  {
    "id": "789c6577-08ca-416d-bbc3-4599d55b01b2",
    "type": "Motion",
    "description": "On Right Foot, Arms Extended Backwards",
    "category": "",
    "character_type": "human",
    "name": "Male Dance Pose",
    "thumbnail": "https://d99n9xvb9513w.cloudfront.net/thumbnails/motions/150200901/static.png",
    "thumbnail_animated": "https://d99n9xvb9513w.cloudfront.net/thumbnails/motions/150200901/animated.gif",
    "motion_id": "789c6577-08ca-416d-bbc3-4599d55b01b2",
    "motions": null,
    "source": "system"
  },
  {
    "id": "d84ac7d2-650d-4655-bf20-0a6c1f918a17",
    "type": "Motion",
    "description": "Right Leg Forward, Arms Supporting",
    "category": "",
    "character_type": "human",
    "name": "Female Laying Pose",
    "thumbnail": "https://d99n9xvb9513w.cloudfront.net/thumbnails/motions/140400908/static.png",
    "thumbnail_animated": "https://d99n9xvb9513w.cloudfront.net/thumbnails/motions/140400908/animated.gif",
    "motion_id": "d84ac7d2-650d-4655-bf20-0a6c1f918a17",
    "motions": null,
    "source": "system"
  },
  {
    "id": "c9cec14d-b96c-11e4-a802-0aaa78deedf9",
    "type": "Motion",
    "description": "Disarming Bow",
    "category": "",
    "character_type": "human",
    "name": "Standing Disarm Bow",
    "thumbnail": "https://d99n9xvb9513w.cloudfront.net/thumbnails/motions/127690929/static.png",
    "thumbnail_animated": "https://d99n9xvb9513w.cloudfront.net/thumbnails/motions/127690929/animated.gif",
    "motion_id": "c9cec14d-b96c-11e4-a802-0aaa78deedf9",
    "motions": null,
    "source": "system"
  },
  {
    "id": "c9ced017-b96c-11e4-a802-0aaa78deedf9",
    "type": "Motion",
    "description": "Standing Idle With Axe",
    "category": "",
    "character_type": "human",
    "name": "Standing Idle",
    "thumbnail": "https://d99n9xvb9513w.cloudfront.net/thumbnails/motions/128650908/static.png",
    "thumbnail_animated": "https://d99n9xvb9513w.cloudfront.net/thumbnails/motions/128650908/animated.gif",
    "motion_id": "c9ced017-b96c-11e4-a802-0aaa78deedf9",
    "motions": null,
    "source": "system"
  },
  {
    "id": "c9c64e6f-b96c-11e4-a802-0aaa78deedf9",
    "type": "Motion",
    "description": "Male Writing While Seated",
    "category": "",
    "character_type": "human",
    "name": "Writing",
    "thumbnail": "https://d99n9xvb9513w.cloudfront.net/thumbnails/motions/101780901/static.png",
    "thumbnail_animated": "https://d99n9xvb9513w.cloudfront.net/thumbnails/motions/101780901/animated.gif",
    "motion_id": "c9c64e6f-b96c-11e4-a802-0aaa78deedf9",
    "motions": null,
    "source": "system"
  },
  {
    "id": "c9c62e30-b96c-11e4-a802-0aaa78deedf9",
    "type": "Motion",
    "description": "Dying Shot To The Chest Falling On Two Knees",
    "category": "",
    "character_type": "human",
    "name": "Dying",
    "thumbnail": "https://d99n9xvb9513w.cloudfront.net/thumbnails/motions/101200901/static.png",
    "thumbnail_animated": "https://d99n9xvb9513w.cloudfront.net/thumbnails/motions/101200901/animated.gif",
    "motion_id": "c9c62e30-b96c-11e4-a802-0aaa78deedf9",
    "motions": null,
    "source": "system"
  },
  {
    "id": "c9c65293-b96c-11e4-a802-0aaa78deedf9",
    "type": "Motion",
    "description": "Baseball Catcher Pop Fly",
    "category": "",
    "character_type": "human",
    "name": "Baseball Catcher",
    "thumbnail": "https://d99n9xvb9513w.cloudfront.net/thumbnails/motions/101860904/static.png",
    "thumbnail_animated": "https://d99n9xvb9513w.cloudfront.net/thumbnails/motions/101860904/animated.gif",
    "motion_id": "c9c65293-b96c-11e4-a802-0aaa78deedf9",
    "motions": null,
    "source": "system"
  },
  {
    "id": "c9c63255-b96c-11e4-a802-0aaa78deedf9",
    "type": "Motion",
    "description": "Male Drinking",
    "category": "",
    "character_type": "human",
    "name": "Drinking",
    "thumbnail": "https://d99n9xvb9513w.cloudfront.net/thumbnails/motions/101330902/static.png",
    "thumbnail_animated": "https://d99n9xvb9513w.cloudfront.net/thumbnails/motions/101330902/animated.gif",
    "motion_id": "c9c63255-b96c-11e4-a802-0aaa78deedf9",
    "motions": null,
    "source": "system"
  },
  {
    "id": "c9c62472-b96c-11e4-a802-0aaa78deedf9",
    "type": "Motion",
    "description": "Double Front Snap Kick",
    "category": "",
    "character_type": "human",
    "name": "Kicking",
    "thumbnail": "https://d99n9xvb9513w.cloudfront.net/thumbnails/motions/100930901/static.png",
    "thumbnail_animated": "https://d99n9xvb9513w.cloudfront.net/thumbnails/motions/100930901/animated.gif",
    "motion_id": "c9c62472-b96c-11e4-a802-0aaa78deedf9",
    "motions": null,
    "source": "system"
  },
  {
    "id": "c9c61ec1-b96c-11e4-a802-0aaa78deedf9",
    "type": "Motion",
    "description": "Knife On The Rear Hand, Reverse Grip",
    "category": "",
    "character_type": "human",
    "name": "Knife Idle",
    "thumbnail": "https://d99n9xvb9513w.cloudfront.net/thumbnails/motions/100850904/static.png",
    "thumbnail_animated": "https://d99n9xvb9513w.cloudfront.net/thumbnails/motions/100850904/animated.gif",
    "motion_id": "c9c61ec1-b96c-11e4-a802-0aaa78deedf9",
    "motions": null,
    "source": "system"
  },
  {
    "id": "c9d59dfb-b96c-11e4-a802-0aaa78deedf9",
    "type": "MotionPack",
    "description": "brooklyn uprock, crossleg freeze, breakdance ending 1, breakdance ending 2, breakdance ending 3, breakdance footwork 2, breakdance footwork 3, breakdance footwork to idle, breakdance freezes, flair, flair, flair, breakdance footwork 1, breakdance footwork to freeze, breakdance footwork to idle, breakdance freeze var 1, breakdance freeze var 2, breakdance freeze var 3, breakdance freeze var 4, breakdance 1990, breakdance 1990, breakdance 1990, breakdance ready, breakdance ready, breakdance ready, breakdance swipes, breakdance uprock, breakdance uprock, breakdance uprock to ground, breakdance uprock to ground, breakdance uprock var 1 end, breakdance uprock var 1, breakdance uprock var 1 start, breakdance uprock var 2",
    "category": "",
    "character_type": "human",
    "name": "Breakdance Pack",
    "thumbnail": "https://d99n9xvb9513w.cloudfront.net/thumbnails/motion_packs/breakdance/static.png",
    "thumbnail_animated": "https://d99n9xvb9513w.cloudfront.net/thumbnails/motion_packs/breakdance/animated.gif",
    "motion_id": "c9d59dfb-b96c-11e4-a802-0aaa78deedf9",
    "motions": [
      {
        "motion_id": "77e3a83e-b176-11e4-bd74-0a6df5051b85",
        "product_id": "c9cc1b0f-b96c-11e4-a802-0aaa78deedf9",
        "name": "brooklyn uprock"
      },
      {
        "motion_id": "77e3acd0-b176-11e4-bd74-0a6df5051b85",
        "product_id": "c9cc1c35-b96c-11e4-a802-0aaa78deedf9",
        "name": "crossleg freeze"
      },
      {
        "motion_id": "77e3ae7e-b176-11e4-bd74-0a6df5051b85",
        "product_id": "c9cc1d13-b96c-11e4-a802-0aaa78deedf9",
        "name": "breakdance ending 1"
      },
      {
        "motion_id": "77e3b00e-b176-11e4-bd74-0a6df5051b85",
        "product_id": "c9cc1dea-b96c-11e4-a802-0aaa78deedf9",
        "name": "breakdance ending 2"
      },
      {
        "motion_id": "77e3b3a6-b176-11e4-bd74-0a6df5051b85",
        "product_id": "c9cc1eb2-b96c-11e4-a802-0aaa78deedf9",
        "name": "breakdance ending 3"
      },
      {
        "motion_id": "77e3b54a-b176-11e4-bd74-0a6df5051b85",
        "product_id": "c9cc1f75-b96c-11e4-a802-0aaa78deedf9",
        "name": "breakdance footwork 2"
      },
      {
        "motion_id": "77e3b6e4-b176-11e4-bd74-0a6df5051b85",
        "product_id": "c9cc203b-b96c-11e4-a802-0aaa78deedf9",
        "name": "breakdance footwork 3"
      },
      {
        "motion_id": "77e3ba68-b176-11e4-bd74-0a6df5051b85",
        "product_id": "c9cc20fd-b96c-11e4-a802-0aaa78deedf9",
        "name": "breakdance footwork to idle"
      },
      {
        "motion_id": "77e3bc16-b176-11e4-bd74-0a6df5051b85",
        "product_id": "c9cc21c2-b96c-11e4-a802-0aaa78deedf9",
        "name": "breakdance freezes"
      },
      {
        "motion_id": "77e41bde-b176-11e4-bd74-0a6df5051b85",
        "product_id": "c9cc3298-b96c-11e4-a802-0aaa78deedf9",
        "name": "flair"
      },
      {
        "motion_id": "77e41d6e-b176-11e4-bd74-0a6df5051b85",
        "product_id": "c9cc3359-b96c-11e4-a802-0aaa78deedf9",
        "name": "flair"
      },
      {
        "motion_id": "77e41f08-b176-11e4-bd74-0a6df5051b85",
        "product_id": "c9cc3416-b96c-11e4-a802-0aaa78deedf9",
        "name": "flair"
      },
      {
        "motion_id": "77e420a2-b176-11e4-bd74-0a6df5051b85",
        "product_id": "c9cc34d4-b96c-11e4-a802-0aaa78deedf9",
        "name": "breakdance footwork 1"
      },
      {
        "motion_id": "77e424b2-b176-11e4-bd74-0a6df5051b85",
        "product_id": "c9cc3593-b96c-11e4-a802-0aaa78deedf9",
        "name": "breakdance footwork to freeze"
      },
      {
        "motion_id": "77e42660-b176-11e4-bd74-0a6df5051b85",
        "product_id": "c9cc3656-b96c-11e4-a802-0aaa78deedf9",
        "name": "breakdance footwork to idle"
      },
      {
        "motion_id": "77e427fa-b176-11e4-bd74-0a6df5051b85",
        "product_id": "c9cc3715-b96c-11e4-a802-0aaa78deedf9",
        "name": "breakdance freeze var 1"
      },
      {
        "motion_id": "77e4299e-b176-11e4-bd74-0a6df5051b85",
        "product_id": "c9cc37d3-b96c-11e4-a802-0aaa78deedf9",
        "name": "breakdance freeze var 2"
      },
      {
        "motion_id": "77e42b38-b176-11e4-bd74-0a6df5051b85",
        "product_id": "c9cc38a8-b96c-11e4-a802-0aaa78deedf9",
        "name": "breakdance freeze var 3"
      },
      {
        "motion_id": "77e42cc8-b176-11e4-bd74-0a6df5051b85",
        "product_id": "c9cc3970-b96c-11e4-a802-0aaa78deedf9",
        "name": "breakdance freeze var 4"
      },
      {
        "motion_id": "77e42e62-b176-11e4-bd74-0a6df5051b85",
        "product_id": "c9cc3a34-b96c-11e4-a802-0aaa78deedf9",
        "name": "breakdance 1990"
      },
      {
        "motion_id": "77e42ffc-b176-11e4-bd74-0a6df5051b85",
        "product_id": "c9cc3afa-b96c-11e4-a802-0aaa78deedf9",
        "name": "breakdance 1990"
      },
      {
        "motion_id": "77e431aa-b176-11e4-bd74-0a6df5051b85",
        "product_id": "c9cc3bc3-b96c-11e4-a802-0aaa78deedf9",
        "name": "breakdance 1990"
      },
      {
        "motion_id": "77e43358-b176-11e4-bd74-0a6df5051b85",
        "product_id": "c9cc3c8a-b96c-11e4-a802-0aaa78deedf9",
        "name": "breakdance ready"
      },
      {
        "motion_id": "77e434e8-b176-11e4-bd74-0a6df5051b85",
        "product_id": "c9cc3d75-b96c-11e4-a802-0aaa78deedf9",
        "name": "breakdance ready"
      },
      {
        "motion_id": "77e4370e-b176-11e4-bd74-0a6df5051b85",
        "product_id": "c9cc3e41-b96c-11e4-a802-0aaa78deedf9",
        "name": "breakdance ready"
      },
      {
        "motion_id": "77e43b5a-b176-11e4-bd74-0a6df5051b85",
        "product_id": "c9cc3f4a-b96c-11e4-a802-0aaa78deedf9",
        "name": "breakdance swipes"
      },
      {
        "motion_id": "77e43cfe-b176-11e4-bd74-0a6df5051b85",
        "product_id": "c9cc4024-b96c-11e4-a802-0aaa78deedf9",
        "name": "breakdance uprock"
      },
      {
        "motion_id": "77e43ec0-b176-11e4-bd74-0a6df5051b85",
        "product_id": "c9cc40ee-b96c-11e4-a802-0aaa78deedf9",
        "name": "breakdance uprock"
      },
      {
        "motion_id": "77e44208-b176-11e4-bd74-0a6df5051b85",
        "product_id": "c9cc41c3-b96c-11e4-a802-0aaa78deedf9",
        "name": "breakdance uprock to ground"
      },
      {
        "motion_id": "77e443a2-b176-11e4-bd74-0a6df5051b85",
        "product_id": "c9cc428c-b96c-11e4-a802-0aaa78deedf9",
        "name": "breakdance uprock to ground"
      },
      {
        "motion_id": "77e44564-b176-11e4-bd74-0a6df5051b85",
        "product_id": "c9cc435b-b96c-11e4-a802-0aaa78deedf9",
        "name": "breakdance uprock var 1 end"
      },
      {
        "motion_id": "77e448ac-b176-11e4-bd74-0a6df5051b85",
        "product_id": "c9cc4420-b96c-11e4-a802-0aaa78deedf9",
        "name": "breakdance uprock var 1"
      },
      {
        "motion_id": "77e44a46-b176-11e4-bd74-0a6df5051b85",
        "product_id": "c9cc44e7-b96c-11e4-a802-0aaa78deedf9",
        "name": "breakdance uprock var 1 start"
      },
      {
        "motion_id": "77e44bfe-b176-11e4-bd74-0a6df5051b85",
        "product_id": "c9cc45b3-b96c-11e4-a802-0aaa78deedf9",
        "name": "breakdance uprock var 2"
      }
    ],
    "source": "system"
  },
  {
    "id": "c319b7d5-948f-42a7-a299-ec71f9eb5660",
    "type": "MotionPack",
    "description": "standing 1H cast spell 01, standing idle, Standing 1H Magic Attack 01, Standing 1H Magic Attack 02, Standing 1H Magic Attack 03, Standing 2H Cast Spell 01, Standing 2H Magic Area Attack 01, Standing 2H Magic Area Attack 02, Standing 2H Magic Attack 01, Standing 2H Magic Attack 02, Standing 2H Magic Attack 03, Standing 2H Magic Attack 04, Standing 2H Magic Attack 05",
    "category": "",
    "character_type": "human",
    "name": "Magic Spell Pack",
    "thumbnail": "https://d99n9xvb9513w.cloudfront.net/thumbnails/motion_packs/magic_spell_pack/static.png",
    "thumbnail_animated": "https://d99n9xvb9513w.cloudfront.net/thumbnails/motion_packs/magic_spell_pack/animated.gif",
    "motion_id": "c319b7d5-948f-42a7-a299-ec71f9eb5660",
    "motions": [
      {
        "motion_id": "e3f54d7e-c886-43b5-8bac-9d08dfdd59ba",
        "product_id": "4569732c-3f47-466c-bcc7-5beba5d246ce",
        "name": "standing 1H cast spell 01"
      },
      {
        "motion_id": "b0691c64-969f-4bbf-a7e5-1a150011cab4",
        "product_id": "b3bcc81a-5213-451e-bcec-294026c5984a",
        "name": "standing idle"
      },
      {
        "motion_id": "b68faa4a-4eac-4570-b7f5-47098cf7f5f7",
        "product_id": "a3d120fd-c26a-46c7-a4a0-59c1c5d8157c",
        "name": "Standing 1H Magic Attack 01"
      },
      {
        "motion_id": "61f24c69-5354-459e-aaf9-2c6e1dd06141",
        "product_id": "0a8b4b48-38bc-4a45-befc-7858ee6ed45d",
        "name": "Standing 1H Magic Attack 02"
      },
      {
        "motion_id": "046507b8-df90-4b9e-869c-702354fdf0ad",
        "product_id": "1f153edf-914f-4562-9344-5765efc0062d",
        "name": "Standing 1H Magic Attack 03"
      },
      {
        "motion_id": "c303fba5-49a3-4b11-b8f1-58b16e42ed47",
        "product_id": "beb8aa59-89e9-451b-902c-2af4296114c8",
        "name": "Standing 2H Cast Spell 01"
      },
      {
        "motion_id": "29213f91-944a-4fd7-bc8d-7cc1fe540d50",
        "product_id": "3a2c5c31-fe8a-4eb1-98c7-ad6cbb95b547",
        "name": "Standing 2H Magic Area Attack 01"
      },
      {
        "motion_id": "6598de7f-8596-423f-883a-3a0a70506faf",
        "product_id": "60e72547-b769-4191-a071-f9869d22828e",
        "name": "Standing 2H Magic Area Attack 02"
      },
      {
        "motion_id": "dc2ee0bf-b684-427c-8743-f6413489a3c8",
        "product_id": "d3a09098-c43e-49e7-85f3-fcc86760517a",
        "name": "Standing 2H Magic Attack 01"
      },
      {
        "motion_id": "7afe57e2-821c-4a4b-a831-95869aed8bed",
        "product_id": "6e2dad1a-2725-4df2-adb9-20dd3007ca8c",
        "name": "Standing 2H Magic Attack 02"
      },
      {
        "motion_id": "dd6516ad-ee87-4df2-8b6e-639b4664a89f",
        "product_id": "e21d35a0-508c-4ed3-af3d-dac75080d944",
        "name": "Standing 2H Magic Attack 03"
      },
      {
        "motion_id": "5b0ea460-8857-4c72-979b-4e641b4bbe0a",
        "product_id": "dd02f795-4bff-4bfa-9658-b6b7dd10817f",
        "name": "Standing 2H Magic Attack 04"
      },
      {
        "motion_id": "fff2ac34-489c-4931-bdba-1ddc46c73424",
        "product_id": "2779e73d-cd1a-40f7-bc69-22421dba1960",
        "name": "Standing 2H Magic Attack 05"
      }
    ],
    "source": "system"
  },
  {
    "id": "79682eef-415c-46db-8ab3-d4318a7a13fa",
    "type": "Motion",
    "description": "Transition From Crouching To Standing With Bow",
    "category": "",
    "character_type": "human",
    "name": "Crouch To Standing",
    "thumbnail": "https://d99n9xvb9513w.cloudfront.net/thumbnails/motions/127690945/static.png",
    "thumbnail_animated": "https://d99n9xvb9513w.cloudfront.net/thumbnails/motions/127690945/animated.gif",
    "motion_id": "79682eef-415c-46db-8ab3-d4318a7a13fa",
    "motions": null,
    "source": "system"
  },
  {
    "id": "5e1bdcb3-4617-46d8-8d98-5f218b7b0269",
    "type": "Motion",
    "description": "Running  Jump To Standing Idle",
    "category": "",
    "character_type": "human",
    "name": "Standing Torch Jump Running To Standing Idle",
    "thumbnail": "https://d99n9xvb9513w.cloudfront.net/thumbnails/motions/128690920/static.png",
    "thumbnail_animated": "https://d99n9xvb9513w.cloudfront.net/thumbnails/motions/128690920/animated.gif",
    "motion_id": "5e1bdcb3-4617-46d8-8d98-5f218b7b0269",
    "motions": null,
    "source": "system"
  },
  {
    "id": "3bf002cc-5527-4c84-b55c-23db82a48d51",
    "type": "Motion",
    "description": "Left Leg On Object, Left Hand On Knee",
    "category": "",
    "character_type": "human",
    "name": "Male Standing Pose",
    "thumbnail": "https://d99n9xvb9513w.cloudfront.net/thumbnails/motions/150700910/static.png",
    "thumbnail_animated": "https://d99n9xvb9513w.cloudfront.net/thumbnails/motions/150700910/animated.gif",
    "motion_id": "3bf002cc-5527-4c84-b55c-23db82a48d51",
    "motions": null,
    "source": "system"
  },
  {
    "id": "f95846bf-6c0c-4429-81c5-d2d58d110a27",
    "type": "Motion",
    "description": "Pushing With Left Side Of Body",
    "category": "",
    "character_type": "human",
    "name": "Male Action Pose",
    "thumbnail": "https://d99n9xvb9513w.cloudfront.net/thumbnails/motions/150000905/static.png",
    "thumbnail_animated": "https://d99n9xvb9513w.cloudfront.net/thumbnails/motions/150000905/animated.gif",
    "motion_id": "f95846bf-6c0c-4429-81c5-d2d58d110a27",
    "motions": null,
    "source": "system"
  },
  {
    "id": "4ce6d573-d378-4908-9552-42a8a05af500",
    "type": "Motion",
    "description": "Left Elbow Resting On Object",
    "category": "",
    "character_type": "human",
    "name": "Male Standing Pose",
    "thumbnail": "https://d99n9xvb9513w.cloudfront.net/thumbnails/motions/150700913/static.png",
    "thumbnail_animated": "https://d99n9xvb9513w.cloudfront.net/thumbnails/motions/150700913/animated.gif",
    "motion_id": "4ce6d573-d378-4908-9552-42a8a05af500",
    "motions": null,
    "source": "system"
  },
  {
    "id": "d525734f-e335-4711-91c6-283811398fb4",
    "type": "Motion",
    "description": "Leaning Forward, Right Hand Supporting",
    "category": "",
    "character_type": "human",
    "name": "Male Crouch Pose",
    "thumbnail": "https://d99n9xvb9513w.cloudfront.net/thumbnails/motions/150100902/static.png",
    "thumbnail_animated": "https://d99n9xvb9513w.cloudfront.net/thumbnails/motions/150100902/animated.gif",
    "motion_id": "d525734f-e335-4711-91c6-283811398fb4",
    "motions": null,
    "source": "system"
  },
  {
    "id": "1cd09ee2-ba14-464d-9800-cbbbf16a6a2f",
    "type": "Motion",
    "description": "Walking, Arms On Hips",
    "category": "",
    "character_type": "human",
    "name": "Female Locomotion Pose",
    "thumbnail": "https://d99n9xvb9513w.cloudfront.net/thumbnails/motions/140500904/static.png",
    "thumbnail_animated": "https://d99n9xvb9513w.cloudfront.net/thumbnails/motions/140500904/animated.gif",
    "motion_id": "1cd09ee2-ba14-464d-9800-cbbbf16a6a2f",
    "motions": null,
    "source": "system"
  },
  {
    "id": "37a8093d-8cbe-424d-9efd-4b3f19df355a",
    "type": "Motion",
    "description": "Male Walk Forward In A Wide Turn To The Right",
    "category": "",
    "character_type": "human",
    "name": "Catwalk Walk Turn 180 Wide R",
    "thumbnail": "https://d99n9xvb9513w.cloudfront.net/thumbnails/motions/128800928/static.png",
    "thumbnail_animated": "https://d99n9xvb9513w.cloudfront.net/thumbnails/motions/128800928/animated.gif",
    "motion_id": "37a8093d-8cbe-424d-9efd-4b3f19df355a",
    "motions": null,
    "source": "system"
  },
  {
    "id": "03aca155-0078-40a3-a52b-04d3eaa7287d",
    "type": "Motion",
    "description": "Block Reaction",
    "category": "",
    "character_type": "human",
    "name": "Standing Block React Large",
    "thumbnail": "https://d99n9xvb9513w.cloudfront.net/thumbnails/motions/128670922/static.png",
    "thumbnail_animated": "https://d99n9xvb9513w.cloudfront.net/thumbnails/motions/128670922/animated.gif",
    "motion_id": "03aca155-0078-40a3-a52b-04d3eaa7287d",
    "motions": null,
    "source": "system"
  },
  {
    "id": "4c002217-c976-4f99-b479-e0edd507e258",
    "type": "Motion",
    "description": "Female Sequence - Transition To Right Hand On Hip",
    "category": "",
    "character_type": "human",
    "name": "Catwalk Sequence 03",
    "thumbnail": "https://d99n9xvb9513w.cloudfront.net/thumbnails/motions/128700932/static.png",
    "thumbnail_animated": "https://d99n9xvb9513w.cloudfront.net/thumbnails/motions/128700932/animated.gif",
    "motion_id": "4c002217-c976-4f99-b479-e0edd507e258",
    "motions": null,
    "source": "system"
  },
  {
    "id": "c83f15d9-1e31-41c7-a1df-dfd6baa6fb60",
    "type": "Motion",
    "description": "Male Standing Idle 02",
    "category": "",
    "character_type": "human",
    "name": "Catwalk Idle 02",
    "thumbnail": "https://d99n9xvb9513w.cloudfront.net/thumbnails/motions/128800904/static.png",
    "thumbnail_animated": "https://d99n9xvb9513w.cloudfront.net/thumbnails/motions/128800904/animated.gif",
    "motion_id": "c83f15d9-1e31-41c7-a1df-dfd6baa6fb60",
    "motions": null,
    "source": "system"
  },
  {
    "id": "8e84b7ba-606b-4678-89ab-da36be048566",
    "type": "Motion",
    "description": "Female Walk Forward To Idle",
    "category": "",
    "character_type": "human",
    "name": "Catwalk Walk Stop",
    "thumbnail": "https://d99n9xvb9513w.cloudfront.net/thumbnails/motions/128700925/static.png",
    "thumbnail_animated": "https://d99n9xvb9513w.cloudfront.net/thumbnails/motions/128700925/animated.gif",
    "motion_id": "8e84b7ba-606b-4678-89ab-da36be048566",
    "motions": null,
    "source": "system"
  },
  {
    "id": "b6a59d7d-d02d-48e4-ac30-3edee0d2d9e6",
    "type": "Motion",
    "description": "Walking Right While Crouched",
    "category": "",
    "character_type": "human",
    "name": "Crouch Walk Right",
    "thumbnail": "https://d99n9xvb9513w.cloudfront.net/thumbnails/motions/128670908/static.png",
    "thumbnail_animated": "https://d99n9xvb9513w.cloudfront.net/thumbnails/motions/128670908/animated.gif",
    "motion_id": "b6a59d7d-d02d-48e4-ac30-3edee0d2d9e6",
    "motions": null,
    "source": "system"
  },
  {
    "id": "c9cda444-b96c-11e4-a802-0aaa78deedf9",
    "type": "Motion",
    "description": "Watering With A Hose",
    "category": "",
    "character_type": "human",
    "name": "Watering",
    "thumbnail": "https://d99n9xvb9513w.cloudfront.net/thumbnails/motions/126980901/static.png",
    "thumbnail_animated": "https://d99n9xvb9513w.cloudfront.net/thumbnails/motions/126980901/animated.gif",
    "motion_id": "c9cda444-b96c-11e4-a802-0aaa78deedf9",
    "motions": null,
    "source": "system"
  },
  {
    "id": "c9cd9ead-b96c-11e4-a802-0aaa78deedf9",
    "type": "Motion",
    "description": "Kneeling Pulling Up A Plant",
    "category": "",
    "character_type": "human",
    "name": "Pull Plant",
    "thumbnail": "https://d99n9xvb9513w.cloudfront.net/thumbnails/motions/126810901/static.png",
    "thumbnail_animated": "https://d99n9xvb9513w.cloudfront.net/thumbnails/motions/126810901/animated.gif",
    "motion_id": "c9cd9ead-b96c-11e4-a802-0aaa78deedf9",
    "motions": null,
    "source": "system"
  },
  {
    "id": "c9cda2af-b96c-11e4-a802-0aaa78deedf9",
    "type": "Motion",
    "description": "Holding An Object While Turning Left",
    "category": "",
    "character_type": "human",
    "name": "Holding Turn Left",
    "thumbnail": "https://d99n9xvb9513w.cloudfront.net/thumbnails/motions/126910901/static.png",
    "thumbnail_animated": "https://d99n9xvb9513w.cloudfront.net/thumbnails/motions/126910901/animated.gif",
    "motion_id": "c9cda2af-b96c-11e4-a802-0aaa78deedf9",
    "motions": null,
    "source": "system"
  },
  {
    "id": "c9c88244-b96c-11e4-a802-0aaa78deedf9",
    "type": "Motion",
    "description": "Dive Roll While Holding Rifle",
    "category": "",
    "character_type": "human",
    "name": "Dive Roll",
    "thumbnail": "https://d99n9xvb9513w.cloudfront.net/thumbnails/motions/114490901/static.png",
    "thumbnail_animated": "https://d99n9xvb9513w.cloudfront.net/thumbnails/motions/114490901/animated.gif",
    "motion_id": "c9c88244-b96c-11e4-a802-0aaa78deedf9",
    "motions": null,
    "source": "system"
  },
  {
    "id": "c9c88b34-b96c-11e4-a802-0aaa78deedf9",
    "type": "Motion",
    "description": "Crouched Strafe Run From Left To Stop",
    "category": "",
    "character_type": "human",
    "name": "Strafing",
    "thumbnail": "https://d99n9xvb9513w.cloudfront.net/thumbnails/motions/116050902/static.png",
    "thumbnail_animated": "https://d99n9xvb9513w.cloudfront.net/thumbnails/motions/116050902/animated.gif",
    "motion_id": "c9c88b34-b96c-11e4-a802-0aaa78deedf9",
    "motions": null,
    "source": "system"
  },
  {
    "id": "c9c828f8-b96c-11e4-a802-0aaa78deedf9",
    "type": "Motion",
    "description": "Injured And Being Carried To A Safer Place",
    "category": "",
    "character_type": "human",
    "name": "Being Carried",
    "thumbnail": "https://d99n9xvb9513w.cloudfront.net/thumbnails/motions/130420901/static.png",
    "thumbnail_animated": "https://d99n9xvb9513w.cloudfront.net/thumbnails/motions/130420901/animated.gif",
    "motion_id": "c9c828f8-b96c-11e4-a802-0aaa78deedf9",
    "motions": null,
    "source": "system"
  },
  {
    "id": "c9c899a0-b96c-11e4-a802-0aaa78deedf9",
    "type": "Motion",
    "description": "Death From Standing Idle",
    "category": "",
    "character_type": "human",
    "name": "Death",
    "thumbnail": "https://d99n9xvb9513w.cloudfront.net/thumbnails/motions/116070901/static.png",
    "thumbnail_animated": "https://d99n9xvb9513w.cloudfront.net/thumbnails/motions/116070901/animated.gif",
    "motion_id": "c9c899a0-b96c-11e4-a802-0aaa78deedf9",
    "motions": null,
    "source": "system"
  },
  {
    "id": "c9c8877b-b96c-11e4-a802-0aaa78deedf9",
    "type": "Motion",
    "description": "Crouched Strafe Run Right To Stop",
    "category": "",
    "character_type": "human",
    "name": "Strafing",
    "thumbnail": "https://d99n9xvb9513w.cloudfront.net/thumbnails/motions/116040902/static.png",
    "thumbnail_animated": "https://d99n9xvb9513w.cloudfront.net/thumbnails/motions/116040902/animated.gif",
    "motion_id": "c9c8877b-b96c-11e4-a802-0aaa78deedf9",
    "motions": null,
    "source": "system"
  },
  {
    "id": "c9c87375-b96c-11e4-a802-0aaa78deedf9",
    "type": "Motion",
    "description": "Walking Backwards While Aiming Rifle",
    "category": "",
    "character_type": "human",
    "name": "Walking Backwards",
    "thumbnail": "https://d99n9xvb9513w.cloudfront.net/thumbnails/motions/116150902/static.png",
    "thumbnail_animated": "https://d99n9xvb9513w.cloudfront.net/thumbnails/motions/116150902/animated.gif",
    "motion_id": "c9c87375-b96c-11e4-a802-0aaa78deedf9",
    "motions": null,
    "source": "system"
  },
  {
    "id": "c9c84906-b96c-11e4-a802-0aaa78deedf9",
    "type": "Motion",
    "description": "Laying On Back",
    "category": "",
    "character_type": "human",
    "name": "Laying",
    "thumbnail": "https://d99n9xvb9513w.cloudfront.net/thumbnails/motions/130560901/static.png",
    "thumbnail_animated": "https://d99n9xvb9513w.cloudfront.net/thumbnails/motions/130560901/animated.gif",
    "motion_id": "c9c84906-b96c-11e4-a802-0aaa78deedf9",
    "motions": null,
    "source": "system"
  },
  {
    "id": "c9c67dc0-b96c-11e4-a802-0aaa78deedf9",
    "type": "Motion",
    "description": "Zombie Looking Around",
    "category": "",
    "character_type": "human",
    "name": "Zombie Idle",
    "thumbnail": "https://d99n9xvb9513w.cloudfront.net/thumbnails/motions/102250902/static.png",
    "thumbnail_animated": "https://d99n9xvb9513w.cloudfront.net/thumbnails/motions/102250902/animated.gif",
    "motion_id": "c9c67dc0-b96c-11e4-a802-0aaa78deedf9",
    "motions": null,
    "source": "system"
  },
  {
    "id": "c9c6ceb1-b96c-11e4-a802-0aaa78deedf9",
    "type": "Motion",
    "description": "Kneeling Warming Hands Over Campfire",
    "category": "",
    "character_type": "human",
    "name": "Kneel",
    "thumbnail": "https://d99n9xvb9513w.cloudfront.net/thumbnails/motions/107830901/static.png",
    "thumbnail_animated": "https://d99n9xvb9513w.cloudfront.net/thumbnails/motions/107830901/animated.gif",
    "motion_id": "c9c6ceb1-b96c-11e4-a802-0aaa78deedf9",
    "motions": null,
    "source": "system"
  },
  {
    "id": "c9c6e0ad-b96c-11e4-a802-0aaa78deedf9",
    "type": "Motion",
    "description": "Hip Hop Just Listening Dancing Variation",
    "category": "",
    "character_type": "human",
    "name": "Hip Hop Dancing",
    "thumbnail": "https://d99n9xvb9513w.cloudfront.net/thumbnails/motions/108650901/static.png",
    "thumbnail_animated": "https://d99n9xvb9513w.cloudfront.net/thumbnails/motions/108650901/animated.gif",
    "motion_id": "c9c6e0ad-b96c-11e4-a802-0aaa78deedf9",
    "motions": null,
    "source": "system"
  },
  {
    "id": "c9c6f217-b96c-11e4-a802-0aaa78deedf9",
    "type": "Motion",
    "description": "Hip Hop Runningman Dance",
    "category": "",
    "character_type": "human",
    "name": "Hip Hop Dancing",
    "thumbnail": "https://d99n9xvb9513w.cloudfront.net/thumbnails/motions/108780902/static.png",
    "thumbnail_animated": "https://d99n9xvb9513w.cloudfront.net/thumbnails/motions/108780902/animated.gif",
    "motion_id": "c9c6f217-b96c-11e4-a802-0aaa78deedf9",
    "motions": null,
    "source": "system"
  },
  {
    "id": "c9c6f3bd-b96c-11e4-a802-0aaa78deedf9",
    "type": "Motion",
    "description": "Capoeira Kicks",
    "category": "",
    "character_type": "human",
    "name": "Capoeira",
    "thumbnail": "https://d99n9xvb9513w.cloudfront.net/thumbnails/motions/108790902/static.png",
    "thumbnail_animated": "https://d99n9xvb9513w.cloudfront.net/thumbnails/motions/108790902/animated.gif",
    "motion_id": "c9c6f3bd-b96c-11e4-a802-0aaa78deedf9",
    "motions": null,
    "source": "system"
  },
  {
    "id": "c9c7084d-b96c-11e4-a802-0aaa78deedf9",
    "type": "Motion",
    "description": "Back Hand Cross",
    "category": "",
    "character_type": "human",
    "name": "Boxing",
    "thumbnail": "https://d99n9xvb9513w.cloudfront.net/thumbnails/motions/110330901/static.png",
    "thumbnail_animated": "https://d99n9xvb9513w.cloudfront.net/thumbnails/motions/110330901/animated.gif",
    "motion_id": "c9c7084d-b96c-11e4-a802-0aaa78deedf9",
    "motions": null,
    "source": "system"
  },
  {
    "id": "c9c66a19-b96c-11e4-a802-0aaa78deedf9",
    "type": "Motion",
    "description": "Male Jumping Onto Platform",
    "category": "",
    "character_type": "human",
    "name": "Jumping",
    "thumbnail": "https://d99n9xvb9513w.cloudfront.net/thumbnails/motions/102050901/static.png",
    "thumbnail_animated": "https://d99n9xvb9513w.cloudfront.net/thumbnails/motions/102050901/animated.gif",
    "motion_id": "c9c66a19-b96c-11e4-a802-0aaa78deedf9",
    "motions": null,
    "source": "system"
  },
  {
    "id": "c9c6bd18-b96c-11e4-a802-0aaa78deedf9",
    "type": "Motion",
    "description": "Hit Reaction While Holding A Rifle",
    "category": "",
    "character_type": "human",
    "name": "Hit Reaction",
    "thumbnail": "https://d99n9xvb9513w.cloudfront.net/thumbnails/motions/104250908/static.png",
    "thumbnail_animated": "https://d99n9xvb9513w.cloudfront.net/thumbnails/motions/104250908/animated.gif",
    "motion_id": "c9c6bd18-b96c-11e4-a802-0aaa78deedf9",
    "motions": null,
    "source": "system"
  },
  {
    "id": "c9c6947c-b96c-11e4-a802-0aaa78deedf9",
    "type": "Motion",
    "description": "Pointing With Arm Bent",
    "category": "",
    "character_type": "human",
    "name": "Pointing",
    "thumbnail": "https://d99n9xvb9513w.cloudfront.net/thumbnails/motions/102840903/static.png",
    "thumbnail_animated": "https://d99n9xvb9513w.cloudfront.net/thumbnails/motions/102840903/animated.gif",
    "motion_id": "c9c6947c-b96c-11e4-a802-0aaa78deedf9",
    "motions": null,
    "source": "system"
  },
  {
    "id": "c9c6a9f8-b96c-11e4-a802-0aaa78deedf9",
    "type": "Motion",
    "description": "Ready Pose To Standing Putting Back The Rifle",
    "category": "",
    "character_type": "human",
    "name": "Put Back Rifle",
    "thumbnail": "https://d99n9xvb9513w.cloudfront.net/thumbnails/motions/103530902/static.png",
    "thumbnail_animated": "https://d99n9xvb9513w.cloudfront.net/thumbnails/motions/103530902/animated.gif",
    "motion_id": "c9c6a9f8-b96c-11e4-a802-0aaa78deedf9",
    "motions": null,
    "source": "system"
  },
  {
    "id": "c9c66120-b96c-11e4-a802-0aaa78deedf9",
    "type": "Motion",
    "description": "Female Hip Hop 'Running Man' Dancing",
    "category": "",
    "character_type": "human",
    "name": "Hip Hop Dancing",
    "thumbnail": "https://d99n9xvb9513w.cloudfront.net/thumbnails/motions/101960906/static.png",
    "thumbnail_animated": "https://d99n9xvb9513w.cloudfront.net/thumbnails/motions/101960906/animated.gif",
    "motion_id": "c9c66120-b96c-11e4-a802-0aaa78deedf9",
    "motions": null,
    "source": "system"
  },
  {
    "id": "c9ca7d50-b96c-11e4-a802-0aaa78deedf9",
    "type": "Motion",
    "description": "Putt Pre-Shot Grading Routine",
    "category": "",
    "character_type": "human",
    "name": "Golf Pre-Putt",
    "thumbnail": "https://d99n9xvb9513w.cloudfront.net/thumbnails/motions/117000902/static.png",
    "thumbnail_animated": "https://d99n9xvb9513w.cloudfront.net/thumbnails/motions/117000902/animated.gif",
    "motion_id": "c9ca7d50-b96c-11e4-a802-0aaa78deedf9",
    "motions": null,
    "source": "system"
  },
  {
    "id": "c9ca68b5-b96c-11e4-a802-0aaa78deedf9",
    "type": "Motion",
    "description": "Drive Pre-Shot Setup",
    "category": "",
    "character_type": "human",
    "name": "Golf Drive Setup",
    "thumbnail": "https://d99n9xvb9513w.cloudfront.net/thumbnails/motions/116960902/static.png",
    "thumbnail_animated": "https://d99n9xvb9513w.cloudfront.net/thumbnails/motions/116960902/animated.gif",
    "motion_id": "c9ca68b5-b96c-11e4-a802-0aaa78deedf9",
    "motions": null,
    "source": "system"
  },
  {
    "id": "c9c9ff70-b96c-11e4-a802-0aaa78deedf9",
    "type": "Motion",
    "description": "Looking Over Both Shoulders",
    "category": "",
    "character_type": "human",
    "name": "Idle",
    "thumbnail": "https://d99n9xvb9513w.cloudfront.net/thumbnails/motions/118060902/static.png",
    "thumbnail_animated": "https://d99n9xvb9513w.cloudfront.net/thumbnails/motions/118060902/animated.gif",
    "motion_id": "c9c9ff70-b96c-11e4-a802-0aaa78deedf9",
    "motions": null,
    "source": "system"
  },
  {
    "id": "c9c91079-b96c-11e4-a802-0aaa78deedf9",
    "type": "Motion",
    "description": "Knocked Over And Falling To The Ground",
    "category": "",
    "character_type": "human",
    "name": "Falling Down",
    "thumbnail": "https://d99n9xvb9513w.cloudfront.net/thumbnails/motions/136870901/static.png",
    "thumbnail_animated": "https://d99n9xvb9513w.cloudfront.net/thumbnails/motions/136870901/animated.gif",
    "motion_id": "c9c91079-b96c-11e4-a802-0aaa78deedf9",
    "motions": null,
    "source": "system"
  },
  {
    "id": "c9c8d41c-b96c-11e4-a802-0aaa78deedf9",
    "type": "Motion",
    "description": "Pulled Out Of Pilot Seat",
    "category": "",
    "character_type": "human",
    "name": "Pulled From Seat",
    "thumbnail": "https://d99n9xvb9513w.cloudfront.net/thumbnails/motions/135840901/static.png",
    "thumbnail_animated": "https://d99n9xvb9513w.cloudfront.net/thumbnails/motions/135840901/animated.gif",
    "motion_id": "c9c8d41c-b96c-11e4-a802-0aaa78deedf9",
    "motions": null,
    "source": "system"
  },
  {
    "id": "c9c8ecbd-b96c-11e4-a802-0aaa78deedf9",
    "type": "Motion",
    "description": "Crouching From Standing Position",
    "category": "",
    "character_type": "human",
    "name": "Crouching",
    "thumbnail": "https://d99n9xvb9513w.cloudfront.net/thumbnails/motions/137660901/static.png",
    "thumbnail_animated": "https://d99n9xvb9513w.cloudfront.net/thumbnails/motions/137660901/animated.gif",
    "motion_id": "c9c8ecbd-b96c-11e4-a802-0aaa78deedf9",
    "motions": null,
    "source": "system"
  },
  {
    "id": "c9c97a12-b96c-11e4-a802-0aaa78deedf9",
    "type": "Motion",
    "description": "Standing Right Turn",
    "category": "",
    "character_type": "human",
    "name": "Right Turn",
    "thumbnail": "https://d99n9xvb9513w.cloudfront.net/thumbnails/motions/117800906/static.png",
    "thumbnail_animated": "https://d99n9xvb9513w.cloudfront.net/thumbnails/motions/117800906/animated.gif",
    "motion_id": "c9c97a12-b96c-11e4-a802-0aaa78deedf9",
    "motions": null,
    "source": "system"
  },
  {
    "id": "c9c97f8f-b96c-11e4-a802-0aaa78deedf9",
    "type": "Motion",
    "description": "Jumping In Place",
    "category": "",
    "character_type": "human",
    "name": "Jump",
    "thumbnail": "https://d99n9xvb9513w.cloudfront.net/thumbnails/motions/117580901/static.png",
    "thumbnail_animated": "https://d99n9xvb9513w.cloudfront.net/thumbnails/motions/117580901/animated.gif",
    "motion_id": "c9c97f8f-b96c-11e4-a802-0aaa78deedf9",
    "motions": null,
    "source": "system"
  },
  {
    "id": "c9c99350-b96c-11e4-a802-0aaa78deedf9",
    "type": "Motion",
    "description": "Standing Idle",
    "category": "",
    "character_type": "human",
    "name": "Idle",
    "thumbnail": "https://d99n9xvb9513w.cloudfront.net/thumbnails/motions/118050901/static.png",
    "thumbnail_animated": "https://d99n9xvb9513w.cloudfront.net/thumbnails/motions/118050901/animated.gif",
    "motion_id": "c9c99350-b96c-11e4-a802-0aaa78deedf9",
    "motions": null,
    "source": "system"
  },
  {
    "id": "c9c95db7-b96c-11e4-a802-0aaa78deedf9",
    "type": "Motion",
    "description": "Mutant Jump Attack To Idle",
    "category": "",
    "character_type": "human",
    "name": "Mutant Jump Attack",
    "thumbnail": "https://d99n9xvb9513w.cloudfront.net/thumbnails/motions/111990902/static.png",
    "thumbnail_animated": "https://d99n9xvb9513w.cloudfront.net/thumbnails/motions/111990902/animated.gif",
    "motion_id": "c9c95db7-b96c-11e4-a802-0aaa78deedf9",
    "motions": null,
    "source": "system"
  },
  {
    "id": "c9c92388-b96c-11e4-a802-0aaa78deedf9",
    "type": "Motion",
    "description": "Dealing Cards",
    "category": "",
    "character_type": "human",
    "name": "Cards",
    "thumbnail": "https://d99n9xvb9513w.cloudfront.net/thumbnails/motions/112830902/static.png",
    "thumbnail_animated": "https://d99n9xvb9513w.cloudfront.net/thumbnails/motions/112830902/animated.gif",
    "motion_id": "c9c92388-b96c-11e4-a802-0aaa78deedf9",
    "motions": null,
    "source": "system"
  },
  {
    "id": "c9c68f62-b96c-11e4-a802-0aaa78deedf9",
    "type": "Motion",
    "description": "Madeline Walk Like A Cowgirl - 2 Strides Loop",
    "category": "",
    "character_type": "human",
    "name": "Female Tough Walk",
    "thumbnail": "https://d99n9xvb9513w.cloudfront.net/thumbnails/motions/102530902/static.png",
    "thumbnail_animated": "https://d99n9xvb9513w.cloudfront.net/thumbnails/motions/102530902/animated.gif",
    "motion_id": "c9c68f62-b96c-11e4-a802-0aaa78deedf9",
    "motions": null,
    "source": "system"
  },
  {
    "id": "c9c81a1d-b96c-11e4-a802-0aaa78deedf9",
    "type": "Motion",
    "description": "Looking Around At Oneself",
    "category": "",
    "character_type": "human",
    "name": "Look Around",
    "thumbnail": "https://d99n9xvb9513w.cloudfront.net/thumbnails/motions/115520901/static.png",
    "thumbnail_animated": "https://d99n9xvb9513w.cloudfront.net/thumbnails/motions/115520901/animated.gif",
    "motion_id": "c9c81a1d-b96c-11e4-a802-0aaa78deedf9",
    "motions": null,
    "source": "system"
  },
  {
    "id": "c9c7f1df-b96c-11e4-a802-0aaa78deedf9",
    "type": "Motion",
    "description": "Quad Punch Combo",
    "category": "",
    "character_type": "human",
    "name": "Quad Punch",
    "thumbnail": "https://d99n9xvb9513w.cloudfront.net/thumbnails/motions/113830901/static.png",
    "thumbnail_animated": "https://d99n9xvb9513w.cloudfront.net/thumbnails/motions/113830901/animated.gif",
    "motion_id": "c9c7f1df-b96c-11e4-a802-0aaa78deedf9",
    "motions": null,
    "source": "system"
  },
  {
    "id": "c9c7a914-b96c-11e4-a802-0aaa78deedf9",
    "type": "Motion",
    "description": "Thrown Over The Shoulder With A Leg Hook By An Aggressor",
    "category": "",
    "character_type": "human",
    "name": "Shoulder Throw, Victim",
    "thumbnail": "https://d99n9xvb9513w.cloudfront.net/thumbnails/motions/113680902/static.png",
    "thumbnail_animated": "https://d99n9xvb9513w.cloudfront.net/thumbnails/motions/113680902/animated.gif",
    "motion_id": "c9c7a914-b96c-11e4-a802-0aaa78deedf9",
    "motions": null,
    "source": "system"
  },
  {
    "id": "c9c81d97-b96c-11e4-a802-0aaa78deedf9",
    "type": "Motion",
    "description": "Being Picked Up And Carried By Someone",
    "category": "",
    "character_type": "human",
    "name": "Being Carried",
    "thumbnail": "https://d99n9xvb9513w.cloudfront.net/thumbnails/motions/130090901/static.png",
    "thumbnail_animated": "https://d99n9xvb9513w.cloudfront.net/thumbnails/motions/130090901/animated.gif",
    "motion_id": "c9c81d97-b96c-11e4-a802-0aaa78deedf9",
    "motions": null,
    "source": "system"
  },
  {
    "id": "c9c86aa4-b96c-11e4-a802-0aaa78deedf9",
    "type": "Motion",
    "description": "Rolling Left While Aiming Rifle",
    "category": "",
    "character_type": "human",
    "name": "Roll Left",
    "thumbnail": "https://d99n9xvb9513w.cloudfront.net/thumbnails/motions/115790901/static.png",
    "thumbnail_animated": "https://d99n9xvb9513w.cloudfront.net/thumbnails/motions/115790901/animated.gif",
    "motion_id": "c9c86aa4-b96c-11e4-a802-0aaa78deedf9",
    "motions": null,
    "source": "system"
  },
  {
    "id": "c9c8214a-b96c-11e4-a802-0aaa78deedf9",
    "type": "Motion",
    "description": "Being Surprised And Looking Right",
    "category": "",
    "character_type": "human",
    "name": "Reacting",
    "thumbnail": "https://d99n9xvb9513w.cloudfront.net/thumbnails/motions/130820901/static.png",
    "thumbnail_animated": "https://d99n9xvb9513w.cloudfront.net/thumbnails/motions/130820901/animated.gif",
    "motion_id": "c9c8214a-b96c-11e4-a802-0aaa78deedf9",
    "motions": null,
    "source": "system"
  },
  {
    "id": "c9c8f9a7-b96c-11e4-a802-0aaa78deedf9",
    "type": "Motion",
    "description": "Running Tired To Dizzy",
    "category": "",
    "character_type": "human",
    "name": "Running Tired",
    "thumbnail": "https://d99n9xvb9513w.cloudfront.net/thumbnails/motions/137850901/static.png",
    "thumbnail_animated": "https://d99n9xvb9513w.cloudfront.net/thumbnails/motions/137850901/animated.gif",
    "motion_id": "c9c8f9a7-b96c-11e4-a802-0aaa78deedf9",
    "motions": null,
    "source": "system"
  },
  {
    "id": "c9c8d041-b96c-11e4-a802-0aaa78deedf9",
    "type": "Motion",
    "description": "Roll Kick Landing On Hands And Knees",
    "category": "",
    "character_type": "human",
    "name": "Roll Kicking",
    "thumbnail": "https://d99n9xvb9513w.cloudfront.net/thumbnails/motions/135980901/static.png",
    "thumbnail_animated": "https://d99n9xvb9513w.cloudfront.net/thumbnails/motions/135980901/animated.gif",
    "motion_id": "c9c8d041-b96c-11e4-a802-0aaa78deedf9",
    "motions": null,
    "source": "system"
  },
  {
    "id": "c9c8cded-b96c-11e4-a802-0aaa78deedf9",
    "type": "Motion",
    "description": "Kneeling And Inspecting Element With Hands",
    "category": "",
    "character_type": "human",
    "name": "Kneeling Inspecting",
    "thumbnail": "https://d99n9xvb9513w.cloudfront.net/thumbnails/motions/136350901/static.png",
    "thumbnail_animated": "https://d99n9xvb9513w.cloudfront.net/thumbnails/motions/136350901/animated.gif",
    "motion_id": "c9c8cded-b96c-11e4-a802-0aaa78deedf9",
    "motions": null,
    "source": "system"
  },
  {
    "id": "c9c8bc4d-b96c-11e4-a802-0aaa78deedf9",
    "type": "Motion",
    "description": "Vault Over Box And Hide",
    "category": "",
    "character_type": "human",
    "name": "Vault Over Box",
    "thumbnail": "https://d99n9xvb9513w.cloudfront.net/thumbnails/motions/135690901/static.png",
    "thumbnail_animated": "https://d99n9xvb9513w.cloudfront.net/thumbnails/motions/135690901/animated.gif",
    "motion_id": "c9c8bc4d-b96c-11e4-a802-0aaa78deedf9",
    "motions": null,
    "source": "system"
  },
  {
    "id": "c9cb5fda-b96c-11e4-a802-0aaa78deedf9",
    "type": "Motion",
    "description": "Juggling Left Knee Stall Of A Soccer Ball",
    "category": "",
    "character_type": "human",
    "name": "Stall Soccerball",
    "thumbnail": "https://d99n9xvb9513w.cloudfront.net/thumbnails/motions/120920901/static.png",
    "thumbnail_animated": "https://d99n9xvb9513w.cloudfront.net/thumbnails/motions/120920901/animated.gif",
    "motion_id": "c9cb5fda-b96c-11e4-a802-0aaa78deedf9",
    "motions": null,
    "source": "system"
  },
  {
    "id": "c9cb0b78-b96c-11e4-a802-0aaa78deedf9",
    "type": "Motion",
    "description": "High Left Boxing Pivot",
    "category": "",
    "character_type": "human",
    "name": "Left Pivot",
    "thumbnail": "https://d99n9xvb9513w.cloudfront.net/thumbnails/motions/110390902/static.png",
    "thumbnail_animated": "https://d99n9xvb9513w.cloudfront.net/thumbnails/motions/110390902/animated.gif",
    "motion_id": "c9cb0b78-b96c-11e4-a802-0aaa78deedf9",
    "motions": null,
    "source": "system"
  },
  {
    "id": "c9cb653e-b96c-11e4-a802-0aaa78deedf9",
    "type": "Motion",
    "description": "Sitting Ethusiastic Clap",
    "category": "",
    "character_type": "human",
    "name": "Sitting Clap",
    "thumbnail": "https://d99n9xvb9513w.cloudfront.net/thumbnails/motions/116190904/static.png",
    "thumbnail_animated": "https://d99n9xvb9513w.cloudfront.net/thumbnails/motions/116190904/animated.gif",
    "motion_id": "c9cb653e-b96c-11e4-a802-0aaa78deedf9",
    "motions": null,
    "source": "system"
  },
  {
    "id": "c9cc560f-b96c-11e4-a802-0aaa78deedf9",
    "type": "Motion",
    "description": "Sword And Shield Block To Idle",
    "category": "",
    "character_type": "human",
    "name": "Sword And Shield Block",
    "thumbnail": "https://d99n9xvb9513w.cloudfront.net/thumbnails/motions/122830901/static.png",
    "thumbnail_animated": "https://d99n9xvb9513w.cloudfront.net/thumbnails/motions/122830901/animated.gif",
    "motion_id": "c9cc560f-b96c-11e4-a802-0aaa78deedf9",
    "motions": null,
    "source": "system"
  },
  {
    "id": "c9cc7780-b96c-11e4-a802-0aaa78deedf9",
    "type": "Motion",
    "description": "Great Sword 90 Degree Left Turn",
    "category": "",
    "character_type": "human",
    "name": "Great Sword Turn",
    "thumbnail": "https://d99n9xvb9513w.cloudfront.net/thumbnails/motions/122260901/static.png",
    "thumbnail_animated": "https://d99n9xvb9513w.cloudfront.net/thumbnails/motions/122260901/animated.gif",
    "motion_id": "c9cc7780-b96c-11e4-a802-0aaa78deedf9",
    "motions": null,
    "source": "system"
  },
  {
    "id": "c9cc21c2-b96c-11e4-a802-0aaa78deedf9",
    "type": "Motion",
    "description": "Breakdance Freeze Combo",
    "category": "",
    "character_type": "human",
    "name": "Breakdance Freezes",
    "thumbnail": "https://d99n9xvb9513w.cloudfront.net/thumbnails/motions/121860901/static.png",
    "thumbnail_animated": "https://d99n9xvb9513w.cloudfront.net/thumbnails/motions/121860901/animated.gif",
    "motion_id": "c9cc21c2-b96c-11e4-a802-0aaa78deedf9",
    "motions": null,
    "source": "system"
  },
  {
    "id": "c9cbe86b-b96c-11e4-a802-0aaa78deedf9",
    "type": "Motion",
    "description": "Northern Soul Dance Spin Dip And Splits",
    "category": "",
    "character_type": "human",
    "name": "Northern Soul Spin Combo",
    "thumbnail": "https://d99n9xvb9513w.cloudfront.net/thumbnails/motions/121420901/static.png",
    "thumbnail_animated": "https://d99n9xvb9513w.cloudfront.net/thumbnails/motions/121420901/animated.gif",
    "motion_id": "c9cbe86b-b96c-11e4-a802-0aaa78deedf9",
    "motions": null,
    "source": "system"
  },
  {
    "id": "c9c9bc34-b96c-11e4-a802-0aaa78deedf9",
    "type": "Motion",
    "description": "Freehang Drop To Standing",
    "category": "",
    "character_type": "human",
    "name": "Freehang Drop",
    "thumbnail": "https://d99n9xvb9513w.cloudfront.net/thumbnails/motions/118750901/static.png",
    "thumbnail_animated": "https://d99n9xvb9513w.cloudfront.net/thumbnails/motions/118750901/animated.gif",
    "motion_id": "c9c9bc34-b96c-11e4-a802-0aaa78deedf9",
    "motions": null,
    "source": "system"
  },
  {
    "id": "c9c9b5d5-b96c-11e4-a802-0aaa78deedf9",
    "type": "Motion",
    "description": "Braced Hang Hop Up To Another Braced Hang",
    "category": "",
    "character_type": "human",
    "name": "Braced Hang Hop Up",
    "thumbnail": "https://d99n9xvb9513w.cloudfront.net/thumbnails/motions/118620901/static.png",
    "thumbnail_animated": "https://d99n9xvb9513w.cloudfront.net/thumbnails/motions/118620901/animated.gif",
    "motion_id": "c9c9b5d5-b96c-11e4-a802-0aaa78deedf9",
    "motions": null,
    "source": "system"
  },
  {
    "id": "c9caf5b4-b96c-11e4-a802-0aaa78deedf9",
    "type": "Motion",
    "description": "Eight Punch Combo",
    "category": "",
    "character_type": "human",
    "name": "Combo Punch",
    "thumbnail": "https://d99n9xvb9513w.cloudfront.net/thumbnails/motions/113930902/static.png",
    "thumbnail_animated": "https://d99n9xvb9513w.cloudfront.net/thumbnails/motions/113930902/animated.gif",
    "motion_id": "c9caf5b4-b96c-11e4-a802-0aaa78deedf9",
    "motions": null,
    "source": "system"
  },
  {
    "id": "c9ca8bbd-b96c-11e4-a802-0aaa78deedf9",
    "type": "Motion",
    "description": "Male Jumping Over An Obstacle With 2 Hands Planted",
    "category": "",
    "character_type": "human",
    "name": "Jumping",
    "thumbnail": "https://d99n9xvb9513w.cloudfront.net/thumbnails/motions/119760901/static.png",
    "thumbnail_animated": "https://d99n9xvb9513w.cloudfront.net/thumbnails/motions/119760901/animated.gif",
    "motion_id": "c9ca8bbd-b96c-11e4-a802-0aaa78deedf9",
    "motions": null,
    "source": "system"
  },
  {
    "id": "c9ca77de-b96c-11e4-a802-0aaa78deedf9",
    "type": "Motion",
    "description": "Post-Shot Course Correction Var 1",
    "category": "",
    "character_type": "human",
    "name": "Golf Post Shot",
    "thumbnail": "https://d99n9xvb9513w.cloudfront.net/thumbnails/motions/116990904/static.png",
    "thumbnail_animated": "https://d99n9xvb9513w.cloudfront.net/thumbnails/motions/116990904/animated.gif",
    "motion_id": "c9ca77de-b96c-11e4-a802-0aaa78deedf9",
    "motions": null,
    "source": "system"
  }
]
